CHANGES
LICENSE
MANIFEST.in
README.txt
setup.py
django_private_media.egg-info/PKG-INFO
django_private_media.egg-info/SOURCES.txt
django_private_media.egg-info/dependency_links.txt
django_private_media.egg-info/not-zip-safe
django_private_media.egg-info/top_level.txt
private_media/__init__.py
private_media/permissions.py
private_media/servers.py
private_media/storages.py
private_media/urls.py
private_media/views.py