Metadata-Version: 1.0
Name: django-private-media
Version: 0.1.3
Summary: Private media for Django. Check the user's authorization before serving files at PRIVATE_MEDIA_URL, uploaded to PRIVATE_MEDIA_ROOT. Requires Django 1.5.
Home-page: https://github.com/RacingTadpole/django-private-media
Author: Arthur Street
Author-email: arthur@racingtadpole.com
License: BSD License
Keywords: private media xsendfile
Platform: UNKNOWN
Classifier: Environment :: Web Environment
Classifier: Framework :: Django
Classifier: Intended Audience :: Developers
Classifier: License :: OSI Approved :: BSD License
Classifier: Operating System :: OS Independent
Classifier: Programming Language :: Python
Classifier: Programming Language :: Python :: 2.7
Classifier: Topic :: Internet :: WWW/HTTP
Classifier: Topic :: Internet :: WWW/HTTP :: Dynamic Content
